arc_vector_client/__init__.py
arc_vector_client/_pydantic_compat.py
arc_vector_client/arc_vector_client.py
arc_vector_client/arc_vector_fastembed.py
arc_vector_client/arc_vector_remote.py
arc_vector_client/async_arc_vector_client.py
arc_vector_client/async_arc_vector_fastembed.py
arc_vector_client/async_arc_vector_remote.py
arc_vector_client/async_client_base.py
arc_vector_client/client_base.py
arc_vector_client/connection.py
arc_vector_client/conversions/__init__.py
arc_vector_client/conversions/common_types.py
arc_vector_client/conversions/conversion.py
arc_vector_client/fastembed_common.py
arc_vector_client/grpc/__init__.py
arc_vector_client/grpc/arc_vector_pb2.py
arc_vector_client/grpc/arc_vector_pb2_grpc.py
arc_vector_client/grpc/collections_pb2.py
arc_vector_client/grpc/collections_pb2_grpc.py
arc_vector_client/grpc/collections_service_pb2.py
arc_vector_client/grpc/collections_service_pb2_grpc.py
arc_vector_client/grpc/json_with_int_pb2.py
arc_vector_client/grpc/json_with_int_pb2_grpc.py
arc_vector_client/grpc/points_pb2.py
arc_vector_client/grpc/points_pb2_grpc.py
arc_vector_client/grpc/points_service_pb2.py
arc_vector_client/grpc/points_service_pb2_grpc.py
arc_vector_client/grpc/snapshots_service_pb2.py
arc_vector_client/grpc/snapshots_service_pb2_grpc.py
arc_vector_client/http/__init__.py
arc_vector_client/http/api/__init__.py
arc_vector_client/http/api/cluster_api.py
arc_vector_client/http/api/collections_api.py
arc_vector_client/http/api/points_api.py
arc_vector_client/http/api/service_api.py
arc_vector_client/http/api/snapshots_api.py
arc_vector_client/http/api_client.py
arc_vector_client/http/configuration.py
arc_vector_client/http/exceptions.py
arc_vector_client/http/models/__init__.py
arc_vector_client/http/models/models.py
arc_vector_client/local/__init__.py
arc_vector_client/local/arc_vector_local.py
arc_vector_client/local/async_arc_vector_local.py
arc_vector_client/local/distances.py
arc_vector_client/local/geo.py
arc_vector_python-1.6.4.dist-info/LICENSE
arc_vector_python-1.6.4.dist-info/METADATA
arc_vector_python-1.6.4.dist-info/WHEEL
arc_vector_python-1.6.4.dist-info/RECORD
