Metadata-Version: 2.1
Name: arc-vector-python
Version: 1.6.4
Summary: Python Client Library for the Arc Vector Search Engine
Home-page: https://gitee.com/giraffedb/arc-vector-python.git
License: Apache-2.0
Keywords: vector,search,neural,matching,client
Author: yunju.lly
Author-email: lingyun.li@fabarta.com
Requires-Python: >=3.8,<3.13
Classifier: License :: OSI Approved :: Apache Software License
Classifier: Programming Language :: Python :: 3
Classifier: Programming Language :: Python :: 3.8
Classifier: Programming Language :: Python :: 3.9
Classifier: Programming Language :: Python :: 3.10
Classifier: Programming Language :: Python :: 3.11
Provides-Extra: fastembed
Requires-Dist: fastembed (==0.1.1) ; (python_version < "3.12") and (extra == "fastembed")
Requires-Dist: grpcio (>=1.41.0)
Requires-Dist: grpcio-tools (>=1.41.0)
Requires-Dist: httpx[http2] (>=0.14.0)
Requires-Dist: numpy (<1.21) ; python_version < "3.8"
Requires-Dist: numpy (>=1.21) ; python_version >= "3.8" and python_version < "3.12"
Requires-Dist: numpy (>=1.26) ; python_version >= "3.12"
Requires-Dist: portalocker (>=2.7.0,<3.0.0)
Requires-Dist: pydantic (>=1.10.8)
Requires-Dist: urllib3 (>=1.26.14,<2.0.0)
Project-URL: Repository, https://gitee.com/giraffedb/arc-vector-python.git
